rawattr.py
rawattr-0.1.0a0.dist-info/licenses/LICENSE
rawattr-0.1.0a0.dist-info/METADATA
rawattr-0.1.0a0.dist-info/WHEEL
rawattr-0.1.0a0.dist-info/top_level.txt
rawattr-0.1.0a0.dist-info/RECORD
