Metadata-Version: 2.4
Name: rawattr
Version: 0.1.0a0
Summary: Low-level Python attribute access utilities that bypass the descriptor protocol.
Author-email: Jifeng Wu <jifengwu2k@gmail.com>
License-Expression: MIT
Project-URL: Homepage, https://github.com/jifengwu2k/rawattr
Project-URL: Bug Tracker, https://github.com/jifengwu2k/rawattr/issues
Classifier: Programming Language :: Python :: 2
Classifier: Programming Language :: Python :: 3
Classifier: Operating System :: OS Independent
Requires-Python: >=2
License-File: LICENSE
Dynamic: license-file
